mocksafe/__init__.py
mocksafe/plugin.py
mocksafe/apis/__init__.py
mocksafe/apis/bdd/__init__.py
mocksafe/apis/bdd/that.py
mocksafe/apis/bdd/when_then.py
mocksafe/core/__init__.py
mocksafe/core/call_matchers.py
mocksafe/core/call_type_validator.py
mocksafe/core/custom_types.py
mocksafe/core/mock.py
mocksafe/core/mock_property.py
mocksafe/core/spy.py
mocksafe/core/stub.py
mocksafe-0.10.0b0.dist-info/licenses/LICENSE
mocksafe-0.10.0b0.dist-info/METADATA
mocksafe-0.10.0b0.dist-info/WHEEL
mocksafe-0.10.0b0.dist-info/entry_points.txt
mocksafe-0.10.0b0.dist-info/top_level.txt
mocksafe-0.10.0b0.dist-info/RECORD
