Metadata-Version: 2.4
Name: mocksafe
Version: 0.10.0b0
Summary: A mocking library developed to enable static and runtime type checking of your mocks to keep them in sync with production code.
License: MIT License
Project-URL: Documentation, https://mocksafe.readthedocs.io/en/0.6/
Project-URL: Source, https://github.com/dmayo3/mocksafe
Keywords: mock,mocking,typed,typing,typesafe,testing,tests,mocks,magicmock,unittest,stubbing
Classifier: Development Status :: 3 - Alpha
Classifier: Natural Language :: English
Classifier: Environment :: Console
Classifier: Operating System :: OS Independent
Classifier: Intended Audience :: Developers
Classifier: License :: OSI Approved :: MIT License
Classifier: Programming Language :: Python
Classifier: Programming Language :: Python :: 3
Classifier: Programming Language :: Python :: 3.10
Classifier: Programming Language :: Python :: 3.11
Classifier: Programming Language :: Python :: 3.12
Classifier: Programming Language :: Python :: 3.13
Classifier: Programming Language :: Python :: 3 :: Only
Classifier: Programming Language :: Python :: Implementation :: CPython
Classifier: Topic :: Software Development :: Libraries
Classifier: Topic :: Software Development :: Testing
Classifier: Topic :: Software Development :: Testing :: Mocking
Classifier: Topic :: Software Development :: Testing :: Unit
Classifier: Framework :: Pytest
Classifier: Typing :: Typed
Requires-Python: >=3.10
License-File: LICENSE
Provides-Extra: pytest
Requires-Dist: pytest>=8.4.0; extra == "pytest"
Provides-Extra: docs
Requires-Dist: sphinx-rtd-theme>=1.5.0; extra == "docs"
Requires-Dist: pytest>=8.4.0; extra == "docs"
Provides-Extra: dev
Requires-Dist: pre-commit>=4.0.0; extra == "dev"
Requires-Dist: pytest>=8.4.0; extra == "dev"
Requires-Dist: pytest-sugar>=1.0.0; extra == "dev"
Requires-Dist: black>=25.1.0; extra == "dev"
Requires-Dist: pylint>=3.3.0; extra == "dev"
Requires-Dist: flake8>=7.1.0; extra == "dev"
Requires-Dist: flake8-rst-docstrings; extra == "dev"
Requires-Dist: flake8-sphinx-links; extra == "dev"
Requires-Dist: flake8-bugbear; extra == "dev"
Requires-Dist: flake8-annotations; extra == "dev"
Requires-Dist: flake8-bandit; extra == "dev"
Requires-Dist: flake8-simplify; extra == "dev"
Requires-Dist: flake8-warnings; extra == "dev"
Requires-Dist: flake8-eradicate; extra == "dev"
Requires-Dist: pep8-naming; extra == "dev"
Requires-Dist: mypy>=1.17.0; extra == "dev"
Requires-Dist: coverage>=7.10.0; extra == "dev"
Dynamic: license-file
